   {
   /*******************************************************************
   TODO:
   Create a collection of spring/forest green properties that
   will consist of properties that can be changed to a different
   highlighting color, thus creating a configurable theme, rather
   than a collection of themes
   *******************************************************************/




   "$schema": "vscode://schemas/color-theme",
   "type": "dark",
   "semanticHighlighting": false,
   "colors": {
   /*---------------------------------------------------------------------*
                     CONFIGURABLE PROPERTIES
   *----------------------------------------------------------------------*/
   // ICONS
   "icon.foreground": "#20E4FF", // selected
   "tree.indentGuidesStroke": "#20E4FF", // selected
   "editorCursor.foreground": "#20E4FF", //selected
   "terminalCursor.foreground": "#20E4FF", //selected
   "editorCursor.background": "#123454",
   "terminalCursor.background": "#123454",
   "list.hoverForeground": "#00CCFF",
   "statusBar.focusBorder": "#00CCFFCC",
   "statusBarItem.focusBorder": "#00CCFFCC",
   "extensionButton.prominentForeground": "#00CCFF",
   "list.inactiveSelectionIconForeground": "#20E4FF",
   "editorGutter.foldingControlForeground": "#20E4FF",
   // CURSOR COLORS
   "terminalOverviewRuler.cursorForeground": "#00FF66",
   // SELECTION HIGHLIGHT
   "editor.selectionHighlightBorder": "#FF5500A5",
   "editor.selectionHighlightBackground": "#FF550018",
   "editor.foldBackground": "#00000044",
   /*---------------------------------------------------------------------*
                     SPECIALIZED/UNIQUELY COLORED
   *-----------------------------------------------------------------------*/
   "contrastBorder": "#FFFFFF2B",
   "disabledForeground": "#AA405CB0",
   "descriptionForeground": "#FF5533",
   "sash.hoverBorder": "#20BCFF",
   "scrollbar.shadow": "#000000",
   "titleBar.border": "#203450", // Unique! (colored as a shadow)
   "editorLightBulb.foreground": "#FFBB11",
   "editorLightBulbAutoFix.foreground": "#FFBB11",
   "editorCodeLens.foreground": "#20BCFF66",
   "editorUnnecessaryCode.opacity": "#AAAAAAAA", // Sets opacity, 'NOT' color!
   "editorUnicodeHighlight.border": "#881111",
   /*---------------------------------------------------------------------*
                        STATUS: ERROR
   *----------------------------------------------------------------------*/
   // ERROR: Fg & Squiggles
   "errorForeground": "#FF2C34",
   "editorError.foreground": "#992222CC",
   "editorError.background": "#FF000011",
   "inputValidation.errorForeground": "#FF2C34",
   "list.errorForeground": "#FF2C34",
   "debugConsole.errorForeground": "#FF2C34",
   "editorOverviewRuler.errorForeground": "#FF2C34",
   "statusBarItem.errorForeground": "#FF2C34",
   // ERROR: Icons
   "notificationsErrorIcon.foreground": "#FF2C34",
   "problemsErrorIcon.foreground": "#FF2C34",
   "debugTokenExpression.error": "#FF2C34",
   "editorMarkerNavigationError.background": "#FF2C3428",
   /*---------------------------------------------------------------------*
                        STATUS: WARNING
   *----------------------------------------------------------------------*/
   // WARNING: Fg & Squiggles
   "editorWarning.foreground": "#FFFF4488",
   "list.warningForeground": "#FFEE11",
   "debugConsole.warningForeground": "#FFEE11",
   "inputValidation.warningForeground": "#FFEE11",
   "editorOverviewRuler.warningForeground": "#FFEE11",
   "statusBarItem.warningForeground": "#FFEE11",
   "inputValidation.warningBorder": "#FFEE11",
   // WARNING: Icons
   "notificationsWarningIcon.foreground": "#FFFF00",
   "problemsWarningIcon.foreground": "#FFFF00",
   /*---------------------------------------------------------------------*
                        STATUS: INFO & HINT
   *----------------------------------------------------------------------*/
   // INFO: Fg & Squiggles
   "editorInfo.border": "#00607080",
   "inputValidation.infoForeground": "#00B0BB",
   "debugConsole.infoForeground": "#00B0BB",
   "editorOverviewRuler.infoForeground": "#00B0BB",
   "editorMarkerNavigationInfo.background": "#00B0BB",
   // INFO: Icons
   "notificationsInfoIcon.foreground": "#20BCFF",
   "problemsInfoIcon.foreground": "#20BCFF",
   "menu.foreground": "#D0D0D0",
   "menu.selectionForeground": "#EEEEEE",
   "menubar.selectionForeground": "#EEEEEE",
   "editorBracketMatch.background": "#00000080",
   "editorBracketMatch.border": "#FFFFFF80",
   "editorOverviewRuler.bracketMatchForeground": "#7030E0",
   // HINT
   "editorHint.border": "#44DD5599",
   "editorHint.foreground": "#44DD55",
   /*------------------------------------------------------------------------*
                                  STATIC BORDERS
   *-------------------------------------------------------------------------*/
   "textBlockQuote.border": "#080000AA",
   "notifications.border": "#080000AA",

   "sideBar.border": "#080000AA",
   "editorOverviewRuler.border": "#080000AA",
   "panelInput.border": "#080000AA",

   "statusBar.noFolderBorder": "#080000",
   "editor.lineHighlightBorder": "#080000",
   /*------------------------------------------------------------------------*
                                TABS & TAB GROUPS
   *-------------------------------------------------------------------------*/
   "tab.lastPinnedBorder": "#335577",
   "tab.border": "#33557780",

   // TAB | Hover Bg
   "tab.hoverBackground": "#001330",
   "tab.unfocusedHoverBackground": "#001330",

   // TAB | Hover Bdr
   "tab.hoverBorder": "#A0F0909F",
   "tab.unfocusedHoverBorder": "#A0F090",

   // TAB | Hover Fg
   "tab.hoverForeground": "#A0F090",
   "tab.unfocusedHoverForeground": "#A0F090",

   // TAB | Active bd
   "tab.activeBorder": "#00AAEE00",
   "tab.unfocusedActiveBorder": "#00AAEE00",
   "tab.activeBorderTop": "#00AAEECC",
   "tab.unfocusedActiveBorderTop": "#00AAEECC",
   "terminal.tab.activeBorder": "#22BBFF",

   // TAB | Active
   "tab.activeBackground": "#001330",
   "tab.unfocusedActiveBackground": "#001330",
   "tab.activeForeground": "#DADADA",
   "tab.unfocusedActiveForeground": "#DADADA",

   // TAB | Inactive
   "tab.inactiveForeground": "#486880",
   "tab.unfocusedInactiveForeground": "#486880",
   "tab.inactiveBackground": "#0B0C0E",
   "tab.unfocusedInactiveBackground": "#0B0C0E",

   // TAB | MISCELLANEOUS HL
   "tab.activeModifiedBorder": "#FFB020",
   "tab.inactiveModifiedBorder": "#FFB020",

   // TAB | Unfocused
   // "tab.unfocusedActiveModifiedBorder": "#FFB020",
   // "tab.unfocusedInactiveModifiedBorder": "#FFB020",

   // EDITOR GROUPS
   "editorGroup.border": "#33557777",
   "editorGroup.dropIntoPromptBorder": "#A0F090",
   "editorGroup.dropIntoPromptForeground": "#A0F090",
   "editorGroup.dropIntoPromptBackground": "#00B0BB66",
   "editorGroup.dropBackground": "#00B0BB66",
   "editorGroup.focusedEmptyBorder": "#EEEEEE99",

   // TAB GROUPS
   "editorGroupHeader.border": "#080000",
   "editorGroupHeader.tabsBorder": "#203450",
   "editorGroupHeader.noTabsBackground": "#0B0C0E",
   "editorGroupHeader.tabsBackground": "#0B0C0E",
   //
   //
   //
   //
   //    ///////////////////////////
   //   ///    MISCELLANEOUS    ///
   //  ///////////////////////////
   //
   //
   //
   //
   "keybindingTable.headerBackground": "#081436",
   "keybindingTable.rowsBackground": "#020724",
   "editor.snippetFinalTabstopHighlightBackground": "#00AC8040",
   "editor.snippetTabstopHighlightBackground": "#00B0BB48",
   "editor.snippetFinalTabstopHighlightBorder": "#00AC80BB",
   "editor.snippetTabstopHighlightBorder": "#00B0BBC5",
   /*---------------------------------------------------------------------*
                     BORDERS, STATIC (colored)
                     (R:051 G:102 B:136 @53)
   *----------------------------------------------------------------------*/
   "activityBar.border": "#080000AA",
   "sideBarSectionHeader.border": "#084A7CEE",
   "panelSectionHeader.border": "#084A7C77",
   "menu.separatorBackground": "#084A7C77",
   "menu.border": "#084A7C77",
   "editorIndentGuide.background": "#084A7C77",
   "keybindingLabel.border": "#084A7C77",
   "statusBar.border": "#FFFFFF36",
   "peekView.border": "#084A7C77",
   "statusBar.debuggingBorder": "#084A7C77",
   "scm.providerBorder": "#084A7C77",
   "panelSection.border": "#084A7C77",
   "terminal.border": "#084A7C",
   "sideBySideEditor.horizontalBorder": "#084A7C77",
   "panel.border": "#084A7CCC",
   /*

   *----------------------------------------------------------------------*
                              ACTIVE
                     (R:016 G:240 B:255 @99)
   *----------------------------------------------------------------------*	*/
   // #CONFIGURABLE - "Active-borders are configurable"
   "activityBar.activeBorder": "#20E4FF",
   "panelTitle.activeBorder": "#20E4FF",


   // ACTIVE FOREGROUND
   "textLink.foreground": "#FF5533",
   "textLink.activeForeground": "#88FF00",
   "notificationLink.foreground": "#77DD22",
   "editorLink.activeForeground": "#77DD22",

   "editorLineNumber.activeForeground": "#EEEEEE",
   "panelTitle.activeForeground": "#EEEEEE",

   "activityBar.foreground": "#EEEEEE",
   "titleBar.activeForeground": "#CACACA",   // COLORED SAME AS MENU/WIDGET FG
   "activityBar.inactiveForeground": "#FFFFFF66",
   "panelTitle.inactiveForeground": "#FFFFFF66",
   "titleBar.inactiveForeground": "#FFFFFF66",

   // ACTIVE BACKGROUND
   "minimapSlider.activeBackground": "#00B0BB77",
   /*

   *----------------------------------------------------------------------*
                     INACTIVE / DE-EMPHASIZED
                        (R51 G192 B136 *53)
   *----------------------------------------------------------------------*/



   "breadcrumb.foreground": "#007799",
   "editorLineNumber.foreground": "#00CCFF66", // #3D7DA0AA
   /*

   *----------------------------------------------------------------------*
                  BACKGROUND, ACTIVE SELECTION   - (op64)
                  BACKGROUND, INACTIVE SELECTION  - (op40)
                     (R:000 G:237 B:255 @99)
   *----------------------------------------------------------------------*/
   "sideBarTitle.foreground": "#22DDFF",
   "editorOverviewRuler.selectionHighlightForeground": "#00CCFF",
   "minimap.selectionOccurrenceHighlight": "#00CCFFAA",
   "minimap.selectionHighlight": "#00CCFF",
   "list.focusOutline": "#FF4400AA",
   "list.inactiveFocusOutline": "#88EEFF6A",
   "list.activeSelectionBackground": "#FF440040",
   "list.inactiveSelectionBackground": "#00CCFF38", // #FF-44-00-33
   "focusBorder": "#FF550077",
   "settings.focusedRowBorder": "#FF550077",
   "menu.selectionBorder": "#00CCFF88",
   "menubar.selectionBorder": "#00CCFF88",
   "menubar.selectionBackground": "#00CCFF3A",
   "selection.background": "#FF550077",
   "editor.selectionBackground": "#FF550077",
   "peekViewResult.selectionBackground": "#17DDFF3A",
   "terminal.selectionBackground": "#00CCFF3A",
   "menu.selectionBackground": "#00CCFF28",
   "editor.inactiveSelectionBackground": "#00CCFF28",
   "quickInputList.focusBackground": "#00CCFF28",

   /*---------------------------------------------------------------------*
                        BORDERS, EMPHASIZED
   *----------------------------------------------------------------------*/

   "pickerGroup.border": "#084A7C",
   "sideBySideEditor.verticalBorder": "#084A7C",

   /*---------------------------------------------------------------------*
                     PRIMARY BACKGROUND PALETTE
            (1|"#121212"), (2|"#0B0C0E"), (3|"#0B1322")
   *----------------------------------------------------------------------*/
   "editor.background": "#121212",
   "editorOverviewRuler.background": "#121212",
   "sideBar.background": "#121212",
   "textBlockQuote.background": "#0B1322",
   "editorMarkerNavigation.background": "#0B1322",
   "welcomePage.tileShadow": "#100000",
   "welcomePage.tileBackground": "#091C30",
   "welcomePage.progress.background": "#20BCFF",
   "welcomePage.tileHoverBackground": "#0080FF33",
   "welcomePage.progress.foreground": "#EEEEEE",

   "panel.background": "#0B1322",
   "activityBar.background": "#0B1322",

   "menu.background": "#0B1322",
   "breadcrumb.background": "#0B1322",
   /*---------------------------------------------------------------------*
                  WORKBENCH'S EMPHASIZED BACKGROUND
   *----------------------------------------------------------------------* */
   "activityBarBadge.background": "#993009",
   "badge.background": "#993009",
   "extensionBadge.remoteBackground": "#084A7C",
   "statusBar.background": "#084A7C",

   "keybindingLabel.background": "#084A7C",

   /*---------------------------------------*
   |> PASTEL-CYAN: #70DCF8
   *----------------------------------------*/
   "editor.wordHighlightBorder": "#70DCF888",
   "peekViewTitleDescription.foreground": "#FF5533",
   "statusBarItem.prominentForeground": "#70DCF8",
   "list.focusForeground": "#70DCF8",
   "minimapSlider.background": "#70DCF82D",
   "keybindingLabel.foreground": "#70DCF8",
   "editor.findMatchBorder": "#90FF00",
   "editor.findMatchBackground": "#000000",
   "editor.findMatchHighlightBackground": "#100050",
   "editor.findMatchHighlightBorder": "#A0AA00",

   /*---------------------------------------*
   |> BLUE-GREEN: #00B0BB
   *----------------------------------------*/
   "ports.iconRunningProcessForeground": "#00B0BB",
   "notificationCenterHeader.foreground": "#00B0BB",
   "progressBar.background": "#084A7C",
   "editor.wordHighlightStrongBorder": "#00B0BB77",
   "peekViewEditor.matchHighlightBorder": "#00B0BB77",
   "editorOverviewRuler.rangeHighlightForeground": "#00B0BB77",
   "editorOverviewRuler.wordHighlightStrongForeground": "#00B0BB55",

   /*---------------------------------------*
   |> TRUE WHITE: #FFFFFF
   *----------------------------------------*/
   "editor.lineHighlightBackground": "#FFFFFF08", // Unique
   "editorWhitespace.foreground": "#FFFFFF22",
   "terminal.selectionForeground": "#FFFFFF",
   "peekViewResult.selectionForeground": "#FFFFFF",
   "breadcrumb.activeSelectionForeground": "#FFFFFF",
   "list.activeSelectionForeground": "#FFFFFF",
   "editor.selectionForeground": "#FFFFFF",
   "list.activeSelectionIconForeground": "#FFFFFF", //   ICON FG
   "statusBar.foreground": "#FFFFFF",
   "list.deemphasizedForeground": "#FFFFFF66",
   "gitDecoration.ignoredResourceForeground": "#FFFFFF50",

   "quickInputList.focusForeground": "#FFFFFF",
   "badge.foreground": "#FFFFFF",
   "activityBarBadge.foreground": "#FFFFFF",
   "extensionBadge.remoteForeground": "#FFFFFF",
   "scrollbarSlider.background": "#FFFFFF66",
   "scrollbarSlider.activeBackground": "#FF4400CC",
   "scrollbarSlider.hoverBackground": "#00CCFFBB",
   // |====================| WHITE: D0D0D0 |====================|
   "foreground": "#D0D0D0",
   "sideBar.foreground": "#D0D0D0",
   "list.inactiveSelectionForeground": "#D0D0D0",
   "editor.foreground": "#D0D0D0",
   "peekViewTitleLabel.foreground": "#D0D0D0",


   "list.focusHighlightForeground": "#D0D0D0",
   "terminal.foreground": "#D5D5D5",
   "textPreformat.foreground": "#EEEEEE",
   "pickerGroup.foreground": "#D0D0D0",
   "activityBar.dropBorder": "#00B0BB",
   "panel.dropBorder": "#00B0BB",

   "terminal.dropBackground": "#00B0BB66",

   "sideBar.dropBackground": "#00B0BB66",
   "list.dropBackground": "#00B0BB66",
   "panelSection.dropBackground": "#00B0BB66",
   "editorRuler.foreground": "#60100030",




   /*---------------------------------------------------------------------*
            GIT/REPOSITORY HIGHLIGHTING & DECORATIONS
   *----------------------------------------------------------------------*/
   // |===================| SCM: MODIFIED |===================|
   "gitDecoration.stageModifiedResourceForeground": "#FDC268",
   "gitDecoration.modifiedResourceForeground": "#FDC268",
   "remoteHub.decorations.modifiedForegroundColor": "#FDC268",
   "remoteHub.decorations.incomingModifiedForegroundColor": "#FDC268",
   "remoteHub.decorations.workspaceRepositoriesView.hasUncommittedChangesForegroundColor": "#FDC268",
   "editorGutter.modifiedBackground": "#FDC268",
   "minimapGutter.modifiedBackground": "#FDC268",
   "editorOverviewRuler.modifiedForeground": "#FDC268",

   // |====================| SCM: ADDED |====================|
   "gitDecoration.untrackedResourceForeground": "#30D0C0",
   "gitDecoration.addedResourceForeground": "#30D0C0",
   "remoteHub.decorations.addedForegroundColor": "#30D0C0",
   "remoteHub.decorations.incomingAddedForegroundColor": "#30D0C0",
   "editorGutter.addedBackground": "#30D0C0",
   "minimapGutter.addedBackground": "#30D0C0",
   "editorOverviewRuler.addedForeground": "#30D0C0",

   // |===================| SCM: DELETED |===================|
   "gitDecoration.deletedResourceForeground": "#EE4499",
   "gitDecoration.stageDeletedResourceForeground": "#EE4499",
   "remoteHub.decorations.deletedForegroundColor": "#EE4499",
   "remoteHub.decorations.incomingDeletedForegroundColor": "#EE4499",
   "editorGutter.deletedBackground": "#EE4499",
   "minimapGutter.deletedBackground": "#EE4499",
   "editorOverviewRuler.deletedForeground": "#EE4499",

   // |=====================| SCM: MISC |=====================|
   "gitDecoration.conflictingResourceForeground": "#FF6666",
   "remoteHub.decorations.conflictForegroundColor": "#FF6666",
   "remoteHub.decorations.possibleConflictForegroundColor": "#FF6666",
   "gitDecoration.renamedResourceForeground": "#BB77FF",
   "remoteHub.decorations.incomingRenamedForegroundColor": "#B060FF",



   /*---------------------------------------------------------------------*
         DIFF EDITOR | DIFF/CHANGE HIGHLIGHTS
   *----------------------------------------------------------------------*/
   "diffEditor.removedLineBackground": "#000000AA",
   "diffEditor.insertedLineBackground": "#000000AA",
   "diffEditor.removedTextBorder": "#D0D0D011",
   "diffEditor.insertedTextBorder": "#D0D0D011",
   "diffEditor.removedTextBackground": "#DD084A7C",
   "diffEditorGutter.removedLineBackground": "#DD601010",
   "diffEditorOverview.removedForeground": "#DD084A7C",
   "diffEditor.insertedTextBackground": "#0020E4FF",
   "diffEditorGutter.insertedLineBackground": "#0022DD77",
   "diffEditorOverview.insertedForeground": "#0020E4FF",
   "diffEditor.border": "#883344CC",
   "diffEditor.diagonalFill": "#200000",
   /*---------------------------------------------------------------------*
                        ANSI 2-BIT PALETTE
   *----------------------------------------------------------------------*/
   "terminal.ansiWhite": "#BEBEBE",
   "terminal.ansiGreen": "#5CC024",
   "terminal.ansiYellow": "#FF9911",
   "terminal.ansiBlue": "#11BBFF",
   "terminal.ansiMagenta": "#FF2266",
   "terminal.ansiRed": "#FF5500",
   "terminal.ansiCyan": "#11CCBB",
   "terminal.ansiBlack": "#003C50",
   "terminal.ansiBrightCyan": "#88FFEE",
   "terminal.ansiBrightMagenta": "#CC99FF",
   "terminal.ansiBrightGreen": "#80D070",
   "terminal.ansiBrightRed": "#FF9080",
   "terminal.ansiBrightYellow": "#DDDD99",
   "terminal.ansiBrightBlue": "#44CCFF",
   "terminal.ansiBrightBlack": "#18324C",
   "terminal.ansiBrightWhite": "#FFFFFF",

   "editorOverviewRuler.wordHighlightForeground": "#70DCF8",
   "editorOverviewRuler.findMatchForeground": "#66EE22", // ~ unique

   "titleBar.activeBackground": "#0B1322",
   "textCodeBlock.background": "#00CCFF2D",

   // PEEK VIEW
   "peekViewTitle.background": "#0A0D1D",
   "peekViewEditor.background": "#090D28",
   "peekViewEditor.matchHighlightBackground": "#555500",
   "peekViewResult.background": "#080A14",
   "peekViewResult.lineForeground": "#FF2299",
   "peekViewResult.fileForeground": "#70D850",


   /*---------------------------------------------------------------------*
                           STATUS-BARS
   *----------------------------------------------------------------------*/
   // STATUS-BAR | DEBUGGER BAR
   "statusBar.debuggingBackground": "#041A30",
   "statusBar.debuggingForeground": "#44FF88",

   // STATUS-BAR | NO-FOLDER BAR
   "statusBar.noFolderBackground": "#203040",
   "statusBar.noFolderForeground": "#999999",
   "statusBarItem.activeBackground": "#00BB77",
   "statusBarItem.remoteBackground": "#0C1224",
   "statusBarItem.remoteForeground": "#00FFCC",
   // STATUS-BAR (status-highlighting)
   /*




   *----------------------------------------------------------------------*
                        FOCUS HIGHLIGHTING
   *----------------------------------------------------------------------*/

   "breadcrumb.focusForeground": "#EEEEEE",

   // ON_HOVER: Highlight-Bg
   "statusBarItem.compactHoverBackground": "#00B0BBB0",
   "statusBarItem.hoverBackground": "#00B0BB55",
   "statusBarItem.prominentHoverBackground": "#00B0BB55",
   "minimapSlider.hoverBackground": "#00B0BB55",

   "list.hoverBackground": "#00B0BB33",
   // Tool Bar
   "toolbar.activeBackground": "#00BB7755",
   "toolbar.hoverBackground": "#00B0BB66",

   // BUTTONS
   "button.border": "#050000",

   // BUTTON PRIMARY
   "button.background": "#00344C",
   "button.hoverBackground": "#004466", // UNIQUE
   "button.foreground": "#D0D0D0",

   // BUTTON SECONDARY
   "button.secondaryBackground": "#003070",
   "button.secondaryHoverBackground": "#004078", // UNIQUE
   "button.secondaryForeground": "#D0D0D0",

   // EXTENSION BUTTON
   "extensionButton.prominentBackground": "#007733",

   // INPUT OPTIONS
   "inputOption.activeBorder": "#20E4FF",
   "inputOption.activeForeground": "#00C8F0",
   "inputOption.activeBackground": "#000A20",
   "inputOption.hoverBackground": "#00BBEE66",

   // TEXT-INPUTS
   "input.placeholderForeground": "#00BBEE66",
   "input.background": "#000A20",
   "input.foreground": "#FFFFFF",
   "input.border": "#123454",

   // CHECKBOX
   "checkbox.foreground": "#22CCFF",
   "checkbox.border": "#007799",
   "checkbox.background": "#000A20",

   // DROPDOWN
   "dropdown.background": "#000A20",
   "dropdown.listBackground": "#000A20",
   "dropdown.foreground": "#5DD8FF",
   "dropdown.border": "#00BBEE77",

   // SETTINGS
   "settings.numberInputForeground": "#80D050",
   "settings.textInputForeground": "#DADADA",
   "settings.dropdownForeground": "#DADADA",
   "settings.textInputBorder": "#123454",
   "settings.numberInputBorder": "#123454",
   "settings.dropdownBorder": "#123454",
   "settings.checkboxBackground": "#000C1C",
   "settings.numberInputBackground": "#000C1C",
   "settings.dropdownBackground": "#000C1C",
   "settings.textInputBackground": "#000C1C",
   "settings.headerForeground": "#D0D0D0",
   "settings.modifiedItemIndicator": "#EEAA33",
   "settings.headerBorder": "#084A7C",
   "settings.sashBorder": "#084A7C",
   "settings.rowHoverBackground": "#FFFFFF11",
   "settings.focusedRowBackground": "#11447777",
   "debugToolBar.background": "#000A20",
   "debugConsoleInputIcon.foreground": "#00FF00",
   "quickInputList.focusIconForeground": "#60FF00EE",
   /*
   *------------------------------------------------------------------------*
                     WIDGETS & INTERACTIVE ITEMS
   *------------------------------------------------------------------------*	*/
   "editorHoverWidget.highlightForeground": "#00CCFF",
   "widget.shadow": "#000000",
   "editorSuggestWidget.background": "#0E1825",
   "editorSuggestWidgetStatus.foreground": "#DADADA",
   "editorSuggestWidget.selectedForeground": "#FFFFFF",
   "editorSuggestWidget.selectedIconForeground": "#20E4FF",
   "editorSuggestWidget.focusHighlightForeground": "#00AAFF",
   "editorSuggestWidget.highlightForeground": "#20E4FF",
   "editorSuggestWidget.selectedBackground": "#00CCFF33",
   "editorWidget.foreground": "#DADADA",
   "editorWidget.border": "#084A7C77",
   "editorHoverWidget.border": "#084A7C77",
   "editorWidget.resizeBorder": "#084A7C",
   "editorWidget.background": "#0B1322",
   "editorHoverWidget.foreground": "#D0D0D0",
   "editorHoverWidget.statusBarBackground": "#000A20",
   "editorHoverWidget.background": "#061327",
   "listFilterWidget.noMatchesOutline": "#FF2C34",
   "listFilterWidget.background": "#000D1D",
   "listFilterWidget.outline": "#007755",
   "list.filterMatchBackground": "#ff0000",

   // MISCELLANEOUS (Fold & Hover)
   "editor.hoverHighlightBackground": "#55990040",
   "textSeparator.foreground": "#084A7CCC",

   "notifications.background": "#0D1E24E2",
   "notificationCenterHeader.background": "#0D1E24E2",
   "sideBarSectionHeader.foreground": "#BBBBBB",
   "panelSectionHeader.foreground": "#BBBBBB",

   // BREAK-POINT COLORING
   "debugIcon.breakpointForeground": "#FF3366",
   "debugIcon.disconnectForeground": "#FF3366",
   "debugIcon.breakpointDisabledForeground": "#667788BB",
   "debugIcon.breakpointUnverifiedForeground": "#667788BB",
   "debugIcon.startForeground": "#44FF88",
   "debugIcon.continueForeground": "#44FF88",
   "debugIcon.restartForeground": "#44FF88",
   "debugIcon.stopForeground": "#FF3366",
   "debugIcon.pauseForeground": "#DDEE55",
   "debugView.stateLabelBackground": "#44FF8820",
   "debugView.stateLabelForeground": "#44FF88",
   "debugView.exceptionLabelBackground": "#FF336624",
   "debugView.exceptionLabelForeground": "#FF3366",
   "debugView.valueChangedHighlight": "#004422",
   "debugTokenExpression.value": "#66AA66",
   "debugTokenExpression.boolean": "#CE9EFF",
   "debugTokenExpression.number": "#00AC80",
   "debugTokenExpression.name": "#C4C4C4",
   "debugTokenExpression.string": "#C5C27C",

   // STEP-IN, STEP-OVER & STEP-OUT
   "debugIcon.stepIntoForeground": "#00B0BB",
   "debugIcon.stepOverForeground": "#00B0BB",
   "debugIcon.stepOutForeground": "#00B0BB",
   "debugIcon.stepBackForeground": "#00B0BB",

   // LIST

   "list.invalidItemForeground": "#FF2C34",
   "list.highlightForeground": "#EEEEEE",
   "list.filterMatchBorder": "#119977",
   // Snippet Highlighting
   "extensionIcon.starForeground": "#FFBB11",
   /*---------------------------------------------------------------------*
                        EDITOR-HL | SNIPPETS
   *----------------------------------------------------------------------*/


   /*---------------------------------------------------------------------*
            DICHROMATIC BRACKET-HIGHLIGHTING SCHEME
   *----------------------------------------------------------------------*/
   // BRACKET-PAIRS
   "editorBracketHighlight.foreground1": "#0898A0", // <<- Odd
   "editorBracketHighlight.foreground3": "#0898A0", // <<- Odd
   "editorBracketHighlight.foreground5": "#0898A0", // <<- Odd
   "editorBracketHighlight.foreground2": "#0088FF", // <<- Even
   "editorBracketHighlight.foreground4": "#0088FF", // <<- Even
   "editorBracketHighlight.foreground6": "#0088FF", // <<- Even

   // BRACKET-PAIR-GUIDES (static state)
   "editorBracketPairGuide.background1": "#034244", // <<- Odd
   "editorBracketPairGuide.background3": "#034244", // <<- Odd
   "editorBracketPairGuide.background5": "#034244", // <<- Odd
   "editorBracketPairGuide.background2": "#02447A", // <<- Even
   "editorBracketPairGuide.background4": "#02447A", // <<- Even
   "editorBracketPairGuide.background6": "#02447A", // <<- Even

   // BRACKET-PAIR-GUIDES (active state)
   "editorBracketPairGuide.activeBackground1": "#0898A0",
   "editorBracketPairGuide.activeBackground3": "#0898A0",
   "editorBracketPairGuide.activeBackground5": "#0898A0",
   "editorBracketPairGuide.activeBackground2": "#0088FF",
   "editorBracketPairGuide.activeBackground4": "#0088FF",
   "editorBracketPairGuide.activeBackground6": "#0088FF",

   "editorBracketHighlight.unexpectedBracket.foreground": "#FF2C34",




















   /*---------------------------------------------------------------------*
                        SYMBOL ICONS
            (OUT OF SIGHT & OUT OF MIND FOR RN)
   *----------------------------------------------------------------------*/
   "symbolIcon.arrayForeground": "#2299FF",
   "symbolIcon.textForeground": "#2299FF",
   "symbolIcon.stringForeground": "#2299FF",
   "symbolIcon.colorForeground": "#2299FF",
   "symbolIcon.classForeground": "#2299FF",
   "symbolIcon.structForeground": "#2299FF",
   "symbolIcon.methodForeground": "#2299FF",
   "symbolIcon.constructorForeground": "#2299FF",
   "symbolIcon.functionForeground": "#2299FF",
   "symbolIcon.interfaceForeground": "#2299FF",
   "symbolIcon.keyForeground": "#2299FF",
   "symbolIcon.namespaceForeground": "#2299FF",
   "symbolIcon.objectForeground": "#2299FF",
   "symbolIcon.referenceForeground": "#2299FF",
   "symbolIcon.eventForeground": "#2299FF",
   "symbolIcon.moduleForeground": "#2299FF",
   "symbolIcon.fieldForeground": "#2299FF",
   "symbolIcon.propertyForeground": "#2299FF",
   "symbolIcon.booleanForeground": "#2299FF",
   "symbolIcon.constantForeground": "#2299FF",
   "symbolIcon.nullForeground": "#2299FF",
   "symbolIcon.enumeratorForeground": "#2299FF",
   "symbolIcon.enumeratorMemberForeground": "#2299FF",
   "symbolIcon.fileForeground": "#2299FF",
   "symbolIcon.folderForeground": "#2299FF",
   "symbolIcon.keywordForeground": "#2299FF",
   "symbolIcon.numberForeground": "#2299FF",
   "symbolIcon.operatorForeground": "#2299FF",
   "symbolIcon.packageForeground": "#2299FF",
   "symbolIcon.typeParameterForeground": "#2299FF",
   "symbolIcon.variableForeground": "#2299FF",
   "symbolIcon.unitForeground": "#2299FF",
   "symbolIcon.snippetForeground": "#2299FF",
   /*---------------------------------------------------------------------*
                              HIDDEN ITEMS
   *----------------------------------------------------------------------*/
   "editorInfo.foreground": "#00000000",
   "panelSectionHeader.background": "#00000000",
   "sideBarSectionHeader.background": "#00000000",
   },
   /*



   ||========================================================================||
   ||"SAVE THESE PROPERTIES UNTIL THEY ARE STYLED IN THE "tokenColors" ARRAY"||
   ||==|| "punctuation.definition.directive",                      ||========||
   || "punctuation.definition.template-expression",            ||
   || "meta.preprocessor.include punctuation.definition.string"||
   ||==========================================================||

   *---------------------------------------------------------------------------*
                     SYNTAX HIGHLIGHTING
   *---------------------------------------------------------------------------*

   LITERAL BOOLEAN         -> #EEA0FF
   LITERAL NUMERIC         -> #BBAA44
   LITERAL STRINGS         -> #DDAA99

   VARIABLES               -> #9DBEE8
   VARIABLE DECLARATIONS   -> #1CACFF
   OBJECT-MEMBERS          -> #1CACFF

   CLASS                   -> #BBA0FC
   CLASS-MEMBERS           -> #1CACFF

   FUNCTIONS               -> #30B6AE
   FUNCTION-MEMBERS        -> #30B6AE
   VARIABLE PARAMETERS     -> #DD7050

   ANNOTATIONS (primitive) -> #0099AA (i)
   *****************************************************************************/

   "semanticTokenColors": {
   "class":                "#BBA0FC",
   "interface":            "#BBA0FC",
   "struct":               "#BBA0FC",
   "namespace":            "#BBA0FC",
   "function":             "#30B6AE",
   "method":               "#30B6AE",
   "variable":             "#9DBEE8",
   "property":             "#9DBEE8",
   "variable.declaration": "#1CACFF",
   "property.declaration": "#1CACFF",
   "parameter":            "#DD7050",
   // "type": "#FFF0",
   // "typeParameter""#FFF0",
   },

   "tokenColors": [{
         "name": "COMMENTS",
         "scope": ["comment", "punctuation.definition.comment"],
         "settings": { "foreground": "#8D424D" }
      },{
         "scope":["punctuation.definition.block.tag", "variable.other.jsdoc"],
         "settings": {
            "foreground": "#8D2D1A",
            "fontStyle": "bold"
         }
      },{

         "scope":"storage.type.class.jsdoc",
         "settings": {
            "foreground": "#007EC4",
            "fontStyle": ""
         }

      },{
         "scope":"comment.block.documentation",
         "settings": {
            "foreground": "#587290",
            "fontStyle": "italic"
         }
      },{
         "name": "STRING LITERALS",
         "scope": "string",
         "settings": { "foreground": "#BCBCBC" }
      },{
         "name": "LITERAL",
         "scope": "constant.character",
         "settings": { "foreground": "#C55C6C", "fontStyle": "bold" }
      },{
         "name": "BOOLEAN LITERALS",
         "scope":"constant.language.boolean",
         "settings": { "foreground": "#F2AAEE"}
      },{
         "name": "LITERALS: UNDEFINED, NULL, & NaN",
         "scope":[
            "constant.language.undefined",
            "constant.language.null",
            "constant.language.NaN" // NaN is case sensitive
         ],
         "settings": { "foreground": "#C55C6C"}
      },{
         "name": "LITERALS: NUMERIC",
         "scope":["constant.numeric"],
         "settings": { "foreground": "#A0C050" }
      },{
         "name": "KEYWORDS: STORAGE DECLARATORS",
         "scope":["storage.type", "keyword.control.import"],
         "settings": { "foreground": "#3A8EFA", "fontStyle": ""}
      },{
         "name": "KEYWORDS: CONTROL-FLOW, CONDITIONALS, MODIFIERS, etc",
         "scope":["storage.modifier", "keyword.control", "keyword.other"],
         "settings": { "foreground": "#3A8EFA", "fontStyle": "italic" }
      },{
         "name": "KEYWORDS: OPERATOR EXPRESSIONS",
         "scope":["keyword.operator.new", "keyword.operator.expression"],
         "settings": { "foreground": "#3A8EFA" }
      },{
         "name": "OPERATORS",
         "scope":[
            "keyword.operator",
            "punctuation",
            "meta.brace"
         ],
         "settings": { "foreground": "#A0C7A0"}
      },{
         "name": "PUNCTUATION",
         "scope": ["punctuation.accessor"],
         "settings": { "fontStyle": "bold" }
      },{
         "name": "OPERATORS: OPERATOR-EXPRESSIONS)",
         "scope":[],
         "settings": { "foreground": "#EE6080", "fontStyle": "italic"}
      },{
         "name": "OPERATORS: SMALL UNARY & ARITHMETIC",
         "scope":[
            "keyword.operator.type.annotation",
            // "storage.type.function.arrow",
            // "keyword.operator.increment",
            // "keyword.operator.decrement"
         ],
         "settings": {"foreground": "#DD7050", "fontStyle": "bold"}
      },{
         "name": "VARIABLES (generic)",
         "scope": ["variable"],
         "settings": { "foreground": "#9DBEE8" }
      },{
         "name": "VARIABLES: LANGUAGE DEFINED",
         "scope":["variable.language", "support.variable",],
         "settings": { "foreground": "#1CACFF" }
      },{
         "name": "VARIABLES: THIS (lexically-scoped object)",
         "scope":["variable.language.this"],
         "settings": { "foreground": "#1CACFF", "fontStyle": "italic" }
      },{
         "name": "VARIABLES: PARAMETERS",
         "scope": ["variable.parameter"],
         "settings": { "foreground": "#DD7050" }
      },{
         "name": "VARIABLES: CLASS-MEMBERS & OBJECT-MEMBERS",
         "scope": [
            "variable.object.property",
            "meta.object.member",
            "meta.field.declaration",
            "meta.definition variable",
            "support.variable.property",
         ],
         "settings": { "foreground": "#1CACFF" }
      },{
         "name": "TYPES & CLASSES",
         "scope": [
            "support.type",
            "support.class",
            "entity.name.class",
            "entity.other.inherited-class",
            "entity.name.type",
            "entity.name.namespace",
            "entity.name.interface",
            "entity.other.attribute",
            "entity.name.scope-resolution"
         ],
         "settings": { "foreground": "#BBA0FC" }
      },{
         "name": "FUNCTION: FUNCTION/METHOD DEFINITIONS & CALLS",
         "scope": "entity.name.function",
         "settings": { "foreground": "#30B6AE" }
      },{
         "name": "FUNCTION: DECLARATION",
         "scope": ["meta.definition.function entity.name.function"],
         "settings": { "foreground": "#14ACA4", "fontStyle": "bold" }
      },{
         "name": "FUNCTION: MATH SUPPORT",
         "scope": ["support.function.math"],
         "settings": { "foreground": "#30B6AE", "fontStyle": "italic" }
      },{
         "name": "PRIMITIVE TYPE ANNOTATIONS (TypeScript)",
         "scope": ["support.type.primitive", "punctuation.definition.template-expression"],
         "settings": { "foreground": "#008294", "fontStyle": "italic" }
      },{
         "name": "STRING TEMPLATE: EMBEDDED VARIABLE PUNCTUATION (ECMAScript Languages)",
         "scope": ["punctuation.definition.template-expression"],
         "settings": { "foreground": "#DD7050", "fontStyle": "bold" }
      },{
         "name": "CONSTANT: MATH-SUPPORT",
         "scope": ["support.constant.math"],
         "settings": { "foreground": "#9DBEE8", "fontStyle": "italic" }
      },
      /*------------------------------------------*
                       JSON/JSONC
      *-------------------------------------------*/
      {
         "name": "JSON | KEYS",
         "scope": "support.type.property-name",
         "settings": { "foreground": "#33BBDD" }
      },{
         "name": "JSON | KEYS",
         "scope": "string.quoted.double.json",
         "settings": { "foreground": "#C0C0C0" }
      },{
         "name": "JSON | BOOLEAN LITERALS & NULL",
         "scope":"constant.language.json",
         "settings": { "foreground": "#EE674C","fontStyle": "italic" }
      },
      /*-----------------------------------------*
                  REGULAR EXPRESSIONS
      *------------------------------------------*/
      {
         "name": "REGEX",
         "scope": "string.regexp",
         "settings": { "foreground": "#DD9880" }
      },{
         "name": "REGEX",
         "scope": "string.regexp keyword",
         "settings": { "foreground": "#DD9880" }
      },{
         "name": "REGEX",
         "scope": "string.regexp keyword.operator",
         "settings": { "foreground": "#DD9880" }
      },{
         "name": "REGEX",
         "scope": "string.regexp punctuation.definition",
         "settings": { "foreground": "#DD9880" }
      },
      /*

      *----------------------------------------------------------------------*
                                 TOKENS
      *----------------------------------------------------------------------*/
      {
         "scope": "token.info-token",
         "settings": { "foreground": "#6796E6" }
      },{
         "scope": "token.warn-token",
         "settings": { "foreground": "#CD9731" }
      },{
         "scope": "token.error-token",
         "settings": { "foreground": "#F44747" }
      },{
         "scope": "token.debug-token",
         "settings": { "foreground": "#B267E6" }
      }
   ]
}
